clean_architecture_mongodb_adapter/__init__.py
clean_architecture_mongodb_adapter/basic_mongodb_adapter.py
clean_architecture_mongodb_adapter-0.1.3.dist-info/LICENSE
clean_architecture_mongodb_adapter-0.1.3.dist-info/METADATA
clean_architecture_mongodb_adapter-0.1.3.dist-info/WHEEL
clean_architecture_mongodb_adapter-0.1.3.dist-info/entry_points.txt
clean_architecture_mongodb_adapter-0.1.3.dist-info/top_level.txt
clean_architecture_mongodb_adapter-0.1.3.dist-info/RECORD
