Metadata-Version: 2.1
Name: clean-architecture-mongodb-adapter
Version: 0.1.3
Summary: Concrete implementation of adapter to MongoDB
Home-page: https://github.com/aberriel/clean_architecture_mongodb_adapter
Author: Anselmo Lira (https://github.com/aberriel)
Author-email: anselmo.lira1@gmail.com
License: UNKNOWN
Keywords: clean_architecture_mongodb_adapter
Platform: UNKNOWN
Classifier: Development Status :: 2 - Pre-Alpha
Classifier: Intended Audience :: Developers
Classifier: Natural Language :: English
Classifier: Programming Language :: Python :: 3.9
Requires-Python: >=3.8
License-File: LICENSE
Requires-Dist: bumpversion (==0.6.0)
Requires-Dist: dnspython (==2.1.0)
Requires-Dist: itsdangerous (==2.0.1)
Requires-Dist: pymongo (==3.12.1)
Requires-Dist: python-decouple (==3.5)
Requires-Dist: requests (==2.26.0)
Requires-Dist: clean-architecture-basic-classes (>=0.1.3)
